Metadata-Version: 2.1
Name: mismamente
Version: 0.0.2
Summary: Copy of easy code tutorial.
Home-page: https://github.com/JoseMacevo
Author: Jose Manuel Acevo Garcia
Author-email: acevogarcia@outlook.es
License: MIT
Keywords: mismamente
Platform: UNKNOWN
Classifier: Development Status :: 3 - Alpha
Classifier: Intended Audience :: Developers
Classifier: Topic :: Software Development :: Build Tools
Classifier: License :: OSI Approved :: MIT License
Classifier: Programming Language :: Python :: 3
License-File: LICENSE.txt
